README.md
setup.cfg
setup.py
dsng_distributions_lee/Binomialdistribution.py
dsng_distributions_lee/Gaussiandistribution.py
dsng_distributions_lee/Generaldistribution.py
dsng_distributions_lee/__init__.py
dsng_distributions_lee.egg-info/PKG-INFO
dsng_distributions_lee.egg-info/SOURCES.txt
dsng_distributions_lee.egg-info/dependency_links.txt
dsng_distributions_lee.egg-info/not-zip-safe
dsng_distributions_lee.egg-info/top_level.txt