Metadata-Version: 1.0
Name: dsng-distributions-lee
Version: 0.1
Summary: Gaussian and Binomial distributions
Home-page: UNKNOWN
Author: Lee Hodgkinson
Author-email: lee@logicon.io
License: UNKNOWN
Platform: UNKNOWN
